{"note":"This file is an internal implementation detail to speed up HTML report generation. Its format can change at any time. You might be looking for the JSON report: https://coverage.rtfd.io/cmd.html#cmd-json","format":5,"version":"7.8.0","globals":"8d659c057002443349a56e7c24b4eae4","files":{"z_145eef247bfb46b6___init___py":{"hash":"e6baa73cda2916dad605215f937a92e1","index":{"url":"z_145eef247bfb46b6___init___py.html","file":"src\\__init__.py","description":"","nums":{"precision":0,"n_files":1,"n_statements":0,"n_excluded":0,"n_missing":0,"n_branches":0,"n_partial_branches":0,"n_missing_branches":0}}},"z_145eef247bfb46b6_decorators_py":{"hash":"6ed63e8dfcbc379aa86a094a19fae33e","index":{"url":"z_145eef247bfb46b6_decorators_py.html","file":"src\\decorators.py","description":"","nums":{"precision":0,"n_files":1,"n_statements":21,"n_excluded":0,"n_missing":0,"n_branches":0,"n_partial_branches":0,"n_missing_branches":0}}},"z_145eef247bfb46b6_generators_py":{"hash":"8bd2d01a1d8ea0ac12d2c63b8f10755c","index":{"url":"z_145eef247bfb46b6_generators_py.html","file":"src\\generators.py","description":"","nums":{"precision":0,"n_files":1,"n_statements":21,"n_excluded":0,"n_missing":0,"n_branches":0,"n_partial_branches":0,"n_missing_branches":0}}},"z_145eef247bfb46b6_masks_py":{"hash":"e96602a4bc77d831fc1028c46e2c7225","index":{"url":"z_145eef247bfb46b6_masks_py.html","file":"src\\masks.py","description":"","nums":{"precision":0,"n_files":1,"n_statements":10,"n_excluded":0,"n_missing":0,"n_branches":0,"n_partial_branches":0,"n_missing_branches":0}}},"z_145eef247bfb46b6_processing_py":{"hash":"5866b1b9170fc0eb8c421055c00aa80c","index":{"url":"z_145eef247bfb46b6_processing_py.html","file":"src\\processing.py","description":"","nums":{"precision":0,"n_files":1,"n_statements":18,"n_excluded":0,"n_missing":0,"n_branches":0,"n_partial_branches":0,"n_missing_branches":0}}},"z_145eef247bfb46b6_widget_py":{"hash":"14ea76a1a1a79e61fff65f0b6f4a9aeb","index":{"url":"z_145eef247bfb46b6_widget_py.html","file":"src\\widget.py","description":"","nums":{"precision":0,"n_files":1,"n_statements":26,"n_excluded":0,"n_missing":0,"n_branches":0,"n_partial_branches":0,"n_missing_branches":0}}}}}